tensors_data_class.py
tensors_data_class-0.0.1.dist-info/LICENSE
tensors_data_class-0.0.1.dist-info/METADATA
tensors_data_class-0.0.1.dist-info/WHEEL
tensors_data_class-0.0.1.dist-info/top_level.txt
tensors_data_class-0.0.1.dist-info/RECORD
