Metadata-Version: 2.1
Name: tensors-data-class
Version: 0.0.1
Summary: PyTorch Extension Library for organizing tensors in a form of a structured tree of dataclasses, with built-in support for advanced collating mechanisms
Home-page: https://github.com/eladn/tensors-data-class
Author: Elad Nachmias
Author-email: eladnah@gmail.com
License: MIT
Platform: UNKNOWN
Classifier: Programming Language :: Python :: 3
Classifier: License :: OSI Approved :: MIT License
Classifier: Operating System :: OS Independent
Provides: tensors_data_class
Requires-Dist: pytorch
